Workbook

Sheet Assumptions
A1: DSCR LEAD INTELLIGENCE — MODEL ASSUMPTIONS
A2: South Florida Pilot (Palm Beach + Broward Counties)
A3: All blue values are editable inputs. Black values are calculated.
A5: MARKET DATA
A6: Total FL leads in pipeline | B6: 7537 | D6: Source: merged_enriched.csv (Steps 01-08 complete)
A7: Skip trace matches (Tracerfy) | B7: 2880 | D7: 45% match rate, $57.60 spent
A8: Tier 1 leads (score 50+) | C8: =ROUND(B6*0.12,0) -> 904 | D8: ~10-15% of total per ICP Playbook
A9: Tier 2 leads (score 30-49) | C9: =ROUND(B6*0.3,0) -> 2261 | D9: ~25-35% of total per ICP Playbook
A10: Tier 3 leads (score 15-29) | C10: =ROUND(B6*0.25,0) -> 1884 | D10: ~20-30% of total
A11: Avg DSCR loan size | B11: 385000 | D11: Source: Market research 04_market_sizing_macro.md
A12: LO commission rate | B12: 0.01 | D12: 1% origination fee standard
A13: LO commission per close ($) | C13: =B11*B12 -> 3850
A14: FL share of national DSCR volume | B14: 0.2 | D14: 18-22% per research
A16: COST OF GOODS SOLD (PER LEAD)
A17: Property data (FDOR/state records) | B17: 0 | D17: Free public records
A18: Skip trace (Tracerfy @ $0.02/match, 45% rate) | B18: 0.009 | D18: $0.02 × 0.45 match rate = $0.009 effective
A19: Email validation (MillionVerifier) | B19: 0.0025 | D19: $4.90/2,000 credits
A20: Phone validation (Twilio v2) | B20: 0.008 | D20: $0.008/lookup
A21: DNC scrub (FTC registry) | B21: 0 | D21: Free for first 5 area codes
A22: ATTOM mortgage enrichment | B22: 0 | D22: Using 1,000 free trial credits
A23: TOTAL COGS PER LEAD | B23: =SUM(B17:B22) -> 0.0195
A25: MONTHLY FIXED COSTS
A26: Claude Max subscription | B26: 200 | D26: AI development tool
A27: ATTOM API (post-trial) | B27: 95 | D27: $95/mo starter tier — $0 during trial
A28: Twilio monthly | B28: 15 | D28: Variable ~$15
A29: MillionVerifier top-ups | B29: 5 | D29: ~$4.90/2K credits as needed
A30: DNC/compliance | B30: 40 | D30: FTC re-scrub every 31 days
A31: Sending domain + email warmup | B31: 35 | D31: Instantly.ai or equivalent
A32: Hosting/tools (GitHub, compute) | B32: 10 | D32: Minimal
A33: TOTAL MONTHLY FIXED COSTS | B33: =SUM(B26:B32) -> 400
A35: ATTOM CREDIT ALLOCATION
A36: Total ATTOM credits available | B36: 1000 | D36: New key from Christine (b9fac048...)
A37: Allocated to PB+Broward Tier 1 | B37: 500 | D37: Top-scored leads from 7,537 pipeline
A38: Allocated to PB+Broward Tier 2 | B38: 250 | D38: Secondary prospects
A39: Reserve (demos, troubleshooting) | B39: 250 | D39: Do NOT burn all at once
A40: Expected match rate | B40: 0.65 | D40: 65% based on 26/33 NC test (79%) adjusted conservatively
A41: Expected enriched leads | D41: =(B37+B38)*B40 -> 487.5

Sheet Per-Lead P&L
A1: MODEL A: PER-LEAD PRICING — 12-MONTH P&L PROJECTION
A2: Based on project docs: Semi-Enriched $15/$10, Full Dossier $100/$60, volume discounts 5% increments
A4: PRICING INPUTS
A5: Semi-Enriched Tier 1 (per lead) | B5: 15
A6: Semi-Enriched Tier 2 (per lead) | B6: 10
A7: Full Dossier Tier 1 (per lead) | B7: 100
A8: Full Dossier Tier 2 (per lead) | B8: 60
A9: Avg volume discount applied | B9: 0.1
B11: Month 1 | C11: Month 2 | D11: Month 3 | E11: Month 4 | F11: Month 5 | G11: Month 6 | H11: Month 7 | I11: Month 8 | J11: Month 9 | K11: Month 10 | L11: Month 11 | M11: Month 12
A12: CUSTOMERS (LO)
A13: LO customers buying Semi-Enriched | B13: 1 | C13: 2 | D13: 3 | E13: 4 | F13: 5 | G13: 5 | H13: 6 | I13: 7 | J13: 8 | K13: 8 | L13: 10 | M13: 10
A14: Avg leads/order (semi) | B14: 25 | C14: 25 | D14: 30 | E14: 30 | F14: 35 | G14: 35 | H14: 40 | I14: 40 | J14: 40 | K14: 50 | L14: 50 | M14: 50
A15: LO customers buying Full Dossier | B15: 0 | C15: 1 | D15: 1 | E15: 2 | F15: 2 | G15: 3 | H15: 3 | I15: 4 | J15: 4 | K15: 5 | L15: 5 | M15: 6
A16: Avg leads/order (dossier) | B16: 0 | C16: 5 | D16: 8 | E16: 8 | F16: 10 | G16: 10 | H16: 10 | I16: 12 | J16: 12 | K16: 12 | L16: 15 | M16: 15
A17: CUSTOMERS (BRANCH MGR)
A18: Branch mgr customers | B18: 0 | C18: 0 | D18: 0 | E18: 0 | F18: 1 | G18: 1 | H18: 1 | I18: 2 | J18: 2 | K18: 2 | L18: 3 | M18: 3
A19: Avg leads/order | B19: 0 | C19: 0 | D19: 0 | E19: 0 | F19: 100 | G19: 100 | H19: 120 | I19: 120 | J19: 150 | K19: 150 | L19: 150 | M19: 150
A20: Product mix (% dossier) | B20: 0 | C20: 0 | D20: 0 | E20: 0 | F20: 0.2 | G20: 0.2 | H20: 0.2 | I20: 0.25 | J20: 0.25 | K20: 0.25 | L20: 0.3 | M20: 0.3
A21: CUSTOMERS (RE AGENT)
A22: Agent customers (Semi only) | B22: 0 | C22: 0 | D22: 1 | E22: 2 | F22: 3 | G22: 4 | H22: 5 | I22: 5 | J22: 6 | K22: 7 | L22: 8 | M22: 10
A23: Avg leads/order | B23: 0 | C23: 0 | D23: 25 | E23: 25 | F23: 25 | G23: 30 | H23: 30 | I23: 30 | J23: 35 | K23: 35 | L23: 40 | M23: 40
A24: CUSTOMERS (RE BROKER)
A25: Broker customers | B25: 0 | C25: 0 | D25: 0 | E25: 0 | F25: 0 | G25: 1 | H25: 1 | I25: 1 | J25: 2 | K25: 2 | L25: 2 | M25: 3
A26: Avg leads/order | B26: 0 | C26: 0 | D26: 0 | E26: 0 | F26: 0 | G26: 75 | H26: 75 | I26: 100 | J26: 100 | K26: 100 | L26: 125 | M26: 125
A28: REVENUE CALCULATIONS
A29: LO Semi-Enriched revenue | B29: =B12*B13*$B$5*(1-$B$9) -> 0 | C29: =C12*C13*$B$5*(1-$B$9) -> 0 | D29: =D12*D13*$B$5*(1-$B$9) -> 0 | E29: =E12*E13*$B$5*(1-$B$9) -> 0 | F29: =F12*F13*$B$5*(1-$B$9) -> 0 | G29: =G12*G13*$B$5*(1-$B$9) -> 0 | H29: =H12*H13*$B$5*(1-$B$9) -> 0 | I29: =I12*I13*$B$5*(1-$B$9) -> 0 | ... M29: =M12*M13*$B$5*(1-$B$9) -> 0
A30: LO Full Dossier revenue | B30: =B14*B15*$B$7*(1-$B$9) -> 0 | C30: =C14*C15*$B$7*(1-$B$9) -> 2250 | D30: =D14*D15*$B$7*(1-$B$9) -> 2700 | E30: =E14*E15*$B$7*(1-$B$9) -> 5400 | F30: =F14*F15*$B$7*(1-$B$9) -> 6300 | G30: =G14*G15*$B$7*(1-$B$9) -> 9450 | H30: =H14*H15*$B$7*(1-$B$9) -> 10800 | I30: =I14*I15*$B$7*(1-$B$9) -> 14400 | ... M30: =M14*M15*$B$7*(1-$B$9) -> 27000
A31: Branch Mgr revenue | B31: =B17*B18*((1-B19)*$B$5+B19*$B$7)*(1-$B$9) -> 0 | C31: =C17*C18*((1-C19)*$B$5+C19*$B$7)*(1-$B$9) -> 0 | D31: =D17*D18*((1-D19)*$B$5+D19*$B$7)*(1-$B$9) -> 0 | E31: =E17*E18*((1-E19)*$B$5+E19*$B$7)*(1-$B$9) -> 0 | F31: =F17*F18*((1-F19)*$B$5+F19*$B$7)*(1-$B$9) -> 0 | G31: =G17*G18*((1-G19)*$B$5+G19*$B$7)*(1-$B$9) -> 0 | H31: =H17*H18*((1-H19)*$B$5+H19*$B$7)*(1-$B$9) -> 0 | I31: =I17*I18*((1-I19)*$B$5+I19*$B$7)*(1-$B$9) -> 0 | ... M31: =M17*M18*((1-M19)*$B$5+M19*$B$7)*(1-$B$9) -> 0
A32: Agent revenue (Tier 2 semi) | B32: =B21*B22*$B$6*(1-$B$9) -> 0 | C32: =C21*C22*$B$6*(1-$B$9) -> 0 | D32: =D21*D22*$B$6*(1-$B$9) -> 0 | E32: =E21*E22*$B$6*(1-$B$9) -> 0 | F32: =F21*F22*$B$6*(1-$B$9) -> 0 | G32: =G21*G22*$B$6*(1-$B$9) -> 0 | H32: =H21*H22*$B$6*(1-$B$9) -> 0 | I32: =I21*I22*$B$6*(1-$B$9) -> 0 | ... M32: =M21*M22*$B$6*(1-$B$9) -> 0
A33: Broker revenue (Tier 2 semi) | B33: =B24*B25*$B$6*(1-$B$9) -> 0 | C33: =C24*C25*$B$6*(1-$B$9) -> 0 | D33: =D24*D25*$B$6*(1-$B$9) -> 0 | E33: =E24*E25*$B$6*(1-$B$9) -> 0 | F33: =F24*F25*$B$6*(1-$B$9) -> 0 | G33: =G24*G25*$B$6*(1-$B$9) -> 0 | H33: =H24*H25*$B$6*(1-$B$9) -> 0 | I33: =I24*I25*$B$6*(1-$B$9) -> 0 | ... M33: =M24*M25*$B$6*(1-$B$9) -> 0
A34: TOTAL REVENUE | B34: =B29+B30+B31+B32+B33 -> 0 | C34: =C29+C30+C31+C32+C33 -> 2250 | D34: =D29+D30+D31+D32+D33 -> 2700 | E34: =E29+E30+E31+E32+E33 -> 5400 | F34: =F29+F30+F31+F32+F33 -> 6300 | G34: =G29+G30+G31+G32+G33 -> 9450 | H34: =H29+H30+H31+H32+H33 -> 10800 | I34: =I29+I30+I31+I32+I33 -> 14400 | ... M34: =M29+M30+M31+M32+M33 -> 27000
A35: Total leads sold | B35: =B12*B13+B14*B15+B17*B18+B21*B22+B24*B25 -> 0 | C35: =C12*C13+C14*C15+C17*C18+C21*C22+C24*C25 -> 25 | D35: =D12*D13+D14*D15+D17*D18+D21*D22+D24*D25 -> 30 | E35: =E12*E13+E14*E15+E17*E18+E21*E22+E24*E25 -> 60 | F35: =F12*F13+F14*F15+F17*F18+F21*F22+F24*F25 -> 70 | G35: =G12*G13+G14*G15+G17*G18+G21*G22+G24*G25 -> 105 | H35: =H12*H13+H14*H15+H17*H18+H21*H22+H24*H25 -> 120 | I35: =I12*I13+I14*I15+I17*I18+I21*I22+I24*I25 -> 160 | ... M35: =M12*M13+M14*M15+M17*M18+M21*M22+M24*M25 -> 300
A36: COGS (leads × per-lead cost) | B36: =B35*Assumptions!B23 -> 0 | C36: =C35*Assumptions!B23 -> 0.4875 | D36: =D35*Assumptions!B23 -> 0.585 | E36: =E35*Assumptions!B23 -> 1.17 | F36: =F35*Assumptions!B23 -> 1.365 | G36: =G35*Assumptions!B23 -> 2.0475 | H36: =H35*Assumptions!B23 -> 2.34 | I36: =I35*Assumptions!B23 -> 3.12 | J36: =J35*Assumptions!B23 -> 3.12 | K36: =K35*Assumptions!B23 -> 4.875 | L36: =L35*Assumptions!B23 -> 4.875 | M36: =M35*Assumptions!B23 -> 5.85
A37: Fixed costs (monthly) | B37: =Assumptions!B33 -> 400 | C37: =Assumptions!B33 -> 400 | D37: =Assumptions!B33 -> 400 | E37: =Assumptions!B33 -> 400 | F37: =Assumptions!B33 -> 400 | G37: =Assumptions!B33 -> 400 | H37: =Assumptions!B33 -> 400 | I37: =Assumptions!B33 -> 400 | J37: =Assumptions!B33 -> 400 | K37: =Assumptions!B33 -> 400 | L37: =Assumptions!B33 -> 400 | M37: =Assumptions!B33 -> 400
A38: NET PROFIT | B38: =B34-B36-B37 -> -400 | C38: =C34-C36-C37 -> 1849.5125 | D38: =D34-D36-D37 -> 2299.415 | E38: =E34-E36-E37 -> 4998.83 | F38: =F34-F36-F37 -> 5898.635 | G38: =G34-G36-G37 -> 9047.9525 | H38: =H34-H36-H37 -> 10397.66 | I38: =I34-I36-I37 -> 13996.88 | ... M38: =M34-M36-M37 -> 26594.15
A39: Net Margin | B39: =IF(B34>0,B38/B34,0) -> 0 | C39: =IF(C34>0,C38/C34,0) -> 0.82200556 | D39: =IF(D34>0,D38/D34,0) -> 0.85163519 | E39: =IF(E34>0,E38/E34,0) -> 0.92570926 | F39: =IF(F34>0,F38/F34,0) -> 0.93629127 | G39: =IF(G34>0,G38/G34,0) -> 0.95745529 | H39: =IF(H34>0,H38/H34,0) -> 0.9627463 | I39: =IF(I34>0,I38/I34,0) -> 0.97200556 | ... M39: =IF(M34>0,M38/M34,0) -> 0.98496852
A40: CUMULATIVE NET PROFIT | B40: =B38 -> -400 | C40: =B40+C38 -> 1449.5125 | D40: =C40+D38 -> 3748.9275 | E40: =D40+E38 -> 8747.7575 | F40: =E40+F38 -> 14646.392 | G40: =F40+G38 -> 23694.345 | H40: =G40+H38 -> 34092.005 | I40: =H40+I38 -> 48088.885 | J40: =I40+J38 -> 62085.765 | ... M40: =L40+M38 -> 132870.17

Sheet Subscription P&L
A1: MODEL B: SUBSCRIPTION PRICING — 12-MONTH P&L PROJECTION
A2: Monthly subscription tiers by ICP. Blue values are editable.
A4: SUBSCRIPTION PRICING
A5: LO Starter (25 leads/mo) | B5: 500
A6: LO Growth (50 leads/mo) | B6: 750
A7: Branch Manager (150 leads/mo) | B7: 1500
A8: Agent Starter (25 leads/mo) | B8: 300
A9: Agent Growth (50 leads/mo) | B9: 500
A10: Broker Office (100 leads/mo) | B10: 800
B12: Month 1 | C12: Month 2 | D12: Month 3 | E12: Month 4 | F12: Month 5 | G12: Month 6 | H12: Month 7 | I12: Month 8 | J12: Month 9 | K12: Month 10 | L12: Month 11 | M12: Month 12
A13: LO Starter subscribers | B13: 1 | C13: 2 | D13: 3 | E13: 3 | F13: 4 | G13: 4 | H13: 5 | I13: 5 | J13: 6 | K13: 6 | L13: 7 | M13: 8
A14: LO Growth subscribers | B14: 0 | C14: 0 | D14: 0 | E14: 1 | F14: 1 | G14: 2 | H14: 2 | I14: 3 | J14: 3 | K14: 4 | L14: 4 | M14: 5
A15: Branch Mgr subscribers | B15: 0 | C15: 0 | D15: 0 | E15: 0 | F15: 1 | G15: 1 | H15: 1 | I15: 2 | J15: 2 | K15: 2 | L15: 3 | M15: 3
A16: Agent Starter subscribers | B16: 0 | C16: 0 | D16: 1 | E16: 2 | F16: 3 | G16: 4 | H16: 5 | I16: 5 | J16: 6 | K16: 7 | L16: 8 | M16: 10
A17: Agent Growth subscribers | B17: 0 | C17: 0 | D17: 0 | E17: 0 | F17: 0 | G17: 1 | H17: 1 | I17: 2 | J17: 2 | K17: 3 | L17: 3 | M17: 4
A18: Broker subscribers | B18: 0 | C18: 0 | D18: 0 | E18: 0 | F18: 0 | G18: 0 | H18: 1 | I18: 1 | J18: 1 | K18: 2 | L18: 2 | M18: 3
A20: REVENUE
A21: LO Starter revenue | B21: =B13*$B$5 -> 500 | C21: =C13*$B$5 -> 1000 | D21: =D13*$B$5 -> 1500 | E21: =E13*$B$5 -> 1500 | F21: =F13*$B$5 -> 2000 | G21: =G13*$B$5 -> 2000 | H21: =H13*$B$5 -> 2500 | I21: =I13*$B$5 -> 2500 | ... M21: =M13*$B$5 -> 4000
A22: LO Growth revenue | B22: =B14*$B$6 -> 0 | C22: =C14*$B$6 -> 0 | D22: =D14*$B$6 -> 0 | E22: =E14*$B$6 -> 750 | F22: =F14*$B$6 -> 750 | G22: =G14*$B$6 -> 1500 | H22: =H14*$B$6 -> 1500 | I22: =I14*$B$6 -> 2250 | ... M22: =M14*$B$6 -> 3750
A23: Branch Mgr revenue | B23: =B15*$B$7 -> 0 | C23: =C15*$B$7 -> 0 | D23: =D15*$B$7 -> 0 | E23: =E15*$B$7 -> 0 | F23: =F15*$B$7 -> 1500 | G23: =G15*$B$7 -> 1500 | H23: =H15*$B$7 -> 1500 | I23: =I15*$B$7 -> 3000 | ... M23: =M15*$B$7 -> 4500
A24: Agent Starter revenue | B24: =B16*$B$8 -> 0 | C24: =C16*$B$8 -> 0 | D24: =D16*$B$8 -> 300 | E24: =E16*$B$8 -> 600 | F24: =F16*$B$8 -> 900 | G24: =G16*$B$8 -> 1200 | H24: =H16*$B$8 -> 1500 | I24: =I16*$B$8 -> 1500 | ... M24: =M16*$B$8 -> 3000
A25: Agent Growth revenue | B25: =B17*$B$9 -> 0 | C25: =C17*$B$9 -> 0 | D25: =D17*$B$9 -> 0 | E25: =E17*$B$9 -> 0 | F25: =F17*$B$9 -> 0 | G25: =G17*$B$9 -> 500 | H25: =H17*$B$9 -> 500 | I25: =I17*$B$9 -> 1000 | ... M25: =M17*$B$9 -> 2000
A26: Broker revenue | B26: =B18*$B$10 -> 0 | C26: =C18*$B$10 -> 0 | D26: =D18*$B$10 -> 0 | E26: =E18*$B$10 -> 0 | F26: =F18*$B$10 -> 0 | G26: =G18*$B$10 -> 0 | H26: =H18*$B$10 -> 800 | I26: =I18*$B$10 -> 800 | ... M26: =M18*$B$10 -> 2400
A27: TOTAL REVENUE | B27: =B21+B22+B23+B24+B25+B26 -> 500 | C27: =C21+C22+C23+C24+C25+C26 -> 1000 | D27: =D21+D22+D23+D24+D25+D26 -> 1800 | E27: =E21+E22+E23+E24+E25+E26 -> 2850 | F27: =F21+F22+F23+F24+F25+F26 -> 5150 | G27: =G21+G22+G23+G24+G25+G26 -> 6700 | H27: =H21+H22+H23+H24+H25+H26 -> 8300 | I27: =I21+I22+I23+I24+I25+I26 -> 11050 | ... M27: =M21+M22+M23+M24+M25+M26 -> 19650
A28: Total leads delivered | B28: =B13*25+B14*50+B15*150+B16*25+B17*50+B18*100 -> 25 | C28: =C13*25+C14*50+C15*150+C16*25+C17*50+C18*100 -> 50 | D28: =D13*25+D14*50+D15*150+D16*25+D17*50+D18*100 -> 100 | E28: =E13*25+E14*50+E15*150+E16*25+E17*50+E18*100 -> 175 | F28: =F13*25+F14*50+F15*150+F16*25+F17*50+F18*100 -> 375 | G28: =G13*25+G14*50+G15*150+G16*25+G17*50+G18*100 -> 500 | H28: =H13*25+H14*50+H15*150+H16*25+H17*50+H18*100 -> 650 | I28: =I13*25+I14*50+I15*150+I16*25+I17*50+I18*100 -> 900 | ... M28: =M13*25+M14*50+M15*150+M16*25+M17*50+M18*100 -> 1650
A29: COGS (leads × per-lead cost) | B29: =B28*Assumptions!B23 -> 0.4875 | C29: =C28*Assumptions!B23 -> 0.975 | D29: =D28*Assumptions!B23 -> 1.95 | E29: =E28*Assumptions!B23 -> 3.4125 | F29: =F28*Assumptions!B23 -> 7.3125 | G29: =G28*Assumptions!B23 -> 9.75 | H29: =H28*Assumptions!B23 -> 12.675 | I29: =I28*Assumptions!B23 -> 17.55 | J29: =J28*Assumptions!B23 -> 18.525 | K29: =K28*Assumptions!B23 -> 22.9125 | L29: =L28*Assumptions!B23 -> 26.8125 | M29: =M28*Assumptions!B23 -> 32.175
A30: Fixed costs (monthly) | B30: =Assumptions!B33 -> 400 | C30: =Assumptions!B33 -> 400 | D30: =Assumptions!B33 -> 400 | E30: =Assumptions!B33 -> 400 | F30: =Assumptions!B33 -> 400 | G30: =Assumptions!B33 -> 400 | H30: =Assumptions!B33 -> 400 | I30: =Assumptions!B33 -> 400 | J30: =Assumptions!B33 -> 400 | K30: =Assumptions!B33 -> 400 | L30: =Assumptions!B33 -> 400 | M30: =Assumptions!B33 -> 400
A31: NET PROFIT | B31: =B27-B29-B30 -> 99.5125 | C31: =C27-C29-C30 -> 599.025 | D31: =D27-D29-D30 -> 1398.05 | E31: =E27-E29-E30 -> 2446.5875 | F31: =F27-F29-F30 -> 4742.6875 | G31: =G27-G29-G30 -> 6290.25 | H31: =H27-H29-H30 -> 7887.325 | I31: =I27-I29-I30 -> 10632.45 | ... M31: =M27-M29-M30 -> 19217.825
A32: Net Margin | B32: =IF(B27>0,B31/B27,0) -> 0.199025 | C32: =IF(C27>0,C31/C27,0) -> 0.599025 | D32: =IF(D27>0,D31/D27,0) -> 0.77669444 | E32: =IF(E27>0,E31/E27,0) -> 0.85845175 | F32: =IF(F27>0,F31/F27,0) -> 0.92091019 | G32: =IF(G27>0,G31/G27,0) -> 0.93884328 | H32: =IF(H27>0,H31/H27,0) -> 0.95028012 | I32: =IF(I27>0,I31/I27,0) -> 0.96221267 | ... M32: =IF(M27>0,M31/M27,0) -> 0.97800636
A33: CUMULATIVE NET PROFIT | B33: =B31 -> 99.5125 | C33: =B33+C31 -> 698.5375 | D33: =C33+D31 -> 2096.5875 | E33: =D33+E31 -> 4543.175 | F33: =E33+F31 -> 9285.8625 | G33: =F33+G31 -> 15576.112 | H33: =G33+H31 -> 23463.438 | I33: =H33+I31 -> 34095.887 | J33: =I33+J31 -> 45527.363 | ... M33: =L33+M31 -> 94595.462

Sheet Model Comparison
A1: PRICING MODEL COMPARISON — YEAR 1 SUMMARY
A3: Metric | B3: Per-Lead Model | C3: Subscription Model | D3: Notes
A4: Year 1 Total Revenue | B4: =SUM('Per-Lead P&L'!B34:M34) -> 137700 | C4: =SUM('Subscription P&L'!B27:M27) -> 99550
A5: Year 1 Total COGS | B5: =SUM('Per-Lead P&L'!B36:M36) -> 29.835 | C5: =SUM('Subscription P&L'!B29:M29) -> 154.5375
A6: Year 1 Fixed Costs | B6: =SUM('Per-Lead P&L'!B37:M37) -> 4800 | C6: =SUM('Subscription P&L'!B30:M30) -> 4800
A7: Year 1 Net Profit | B7: =B4-B5-B6 -> 132870.17 | C7: =C4-C5-C6 -> 94595.462
A8: Year 1 Net Margin | B8: =IF(B4>0,B7/B4,0) -> 0.96492495 | C8: =IF(C4>0,C7/C4,0) -> 0.95023066
A9: Month 12 MRR | B9: ='Per-Lead P&L'!M34 -> 27000 | C9: ='Subscription P&L'!M27 -> 19650 | D9: Monthly recurring run rate
A10: Breakeven month | D10: Month where cumulative profit turns positive
A11: Total leads delivered (Year 1) | B11: =SUM('Per-Lead P&L'!B35:M35) -> 1530 | C11: =SUM('Subscription P&L'!B28:M28) -> 7925
A12: Revenue per lead (avg) | B12: =IF(B11>0,B4/B11,0) -> 90 | C12: =IF(C11>0,C4/C11,0) -> 12.561514 | D12: Blended average
A13: COGS per lead | B13: =Assumptions!B23 -> 0.0195 | C13: =Assumptions!B23 -> 0.0195 | D13: Same enrichment cost either way
A16: BUYER ROI ANALYSIS
A17: Avg DSCR loan size | B17: =Assumptions!B11 -> 385000
A18: LO commission per close | B18: =Assumptions!B13 -> 0 | D18: 1% origination fee
A19: Leads needed to close 1 deal (est.) | B19: 50 | D19: 2% conversion rate assumption
A20: Cost of 50 leads (Semi @ $15) | B20: =B19*$B$5 -> 1491.75 | D20: Per-lead model
A21: Cost of 50 leads (Subscription) | B21: =500*2 -> 1000 | D21: 2 months of LO Starter @ $500/mo
A22: ROI per closed deal (Per-Lead) | B22: =(B18-B20)/B20 -> -1 | D22: Commission / lead cost
A23: ROI per closed deal (Subscription) | B23: =(B18-B21)/B21 -> -1 | D23: Commission / subscription cost
